trianglefinal/__init__.py
trianglefinal/triangle.py
Triangle_cs_bj-1.0.0.dist-info/LICENSE.txt
Triangle_cs_bj-1.0.0.dist-info/METADATA
Triangle_cs_bj-1.0.0.dist-info/WHEEL
Triangle_cs_bj-1.0.0.dist-info/top_level.txt
Triangle_cs_bj-1.0.0.dist-info/RECORD
