Metadata-Version: 2.1
Name: Triangle-cs-bj
Version: 1.0.0
Summary: A Python module to compute Triangle stuff
Home-page: https://github.com/pypa/sampleproject
Author: B.Ajay
Author-email: badhrinr@gmail.com
License: UNKNOWN
Platform: UNKNOWN
Classifier: Programming Language :: Python :: 3
Classifier: License :: OSI Approved :: MIT License
Classifier: Operating System :: OS Independent
Requires-Python: >=3.6
